[
  {
    "full_name": "yewstack/yew",
    "stargazers_count": 25039,
    "open_issues_count": 106,
    "forks_count": 1199
  },
  {
    "full_name": "mermaid-js/mermaid",
    "stargazers_count": 51340,
    "open_issues_count": 853,
    "forks_count": 3985
  },
  {
    "full_name": "denoland/deno",
    "stargazers_count": 86283,
    "open_issues_count": 1060,
    "forks_count": 4655
  },
  {
    "full_name": "open-sauced/open-sauced",
    "stargazers_count": 805,
    "open_issues_count": 10,
    "forks_count": 439
  }
]