[
  {
    "full_name": "microsoft/Web-Dev-For-Beginners",
    "stargazers_count": 60920,
    "open_issues_count": 170,
    "forks_count": 9507
  },
  {
    "full_name": "resume/resume.github.com",
    "stargazers_count": 58859,
    "open_issues_count": 59,
    "forks_count": 1374
  },
  {
    "full_name": "rust-lang/rust",
    "stargazers_count": 75290,
    "open_issues_count": 9430,
    "forks_count": 10108
  },
  {
    "full_name": "elm/core",
    "stargazers_count": 2713,
    "open_issues_count": 96,
    "forks_count": 359
  },
  {
    "full_name": "microsoft/vscode",
    "stargazers_count": 139982,
    "open_issues_count": 6857,
    "forks_count": 24204
  }
]